vantage_cli/__init__.py
vantage_cli/auth.py
vantage_cli/cache.py
vantage_cli/client.py
vantage_cli/config.py
vantage_cli/constants.py
vantage_cli/exceptions.py
vantage_cli/gql_client.py
vantage_cli/main.py
vantage_cli/render.py
vantage_cli/schemas.py
vantage_cli/time_loop.py
vantage_cli/apps/__init__.py
vantage_cli/apps/common.py
vantage_cli/apps/templates.py
vantage_cli/apps/utils.py
vantage_cli/apps/jupyterhub_microk8s_localhost/README.md
vantage_cli/apps/jupyterhub_microk8s_localhost/__init__.py
vantage_cli/apps/jupyterhub_microk8s_localhost/app.py
vantage_cli/apps/jupyterhub_microk8s_localhost/constants.py
vantage_cli/apps/jupyterhub_microk8s_localhost/jupyterhub_command.py
vantage_cli/apps/jupyterhub_microk8s_localhost/render.py
vantage_cli/apps/slurm_juju_localhost/__init__.py
vantage_cli/apps/slurm_juju_localhost/app.py
vantage_cli/apps/slurm_juju_localhost/bundle_yaml.py
vantage_cli/apps/slurm_juju_localhost/utils.py
vantage_cli/apps/slurm_microk8s_localhost/README.md
vantage_cli/apps/slurm_microk8s_localhost/__init__.py
vantage_cli/apps/slurm_microk8s_localhost/app.py
vantage_cli/apps/slurm_microk8s_localhost/constants.py
vantage_cli/apps/slurm_microk8s_localhost/render.py
vantage_cli/apps/slurm_microk8s_localhost/utils.py
vantage_cli/apps/slurm_multipass_localhost/__init__.py
vantage_cli/apps/slurm_multipass_localhost/app.py
vantage_cli/apps/slurm_multipass_localhost/utils.py
vantage_cli/commands/__init__.py
vantage_cli/commands/alias/__init__.py
vantage_cli/commands/alias/apps.py
vantage_cli/commands/alias/clouds.py
vantage_cli/commands/alias/clusters.py
vantage_cli/commands/alias/deployments.py
vantage_cli/commands/alias/federations.py
vantage_cli/commands/alias/networks.py
vantage_cli/commands/alias/notebooks.py
vantage_cli/commands/alias/profiles.py
vantage_cli/commands/alias/teams.py
vantage_cli/commands/app/__init__.py
vantage_cli/commands/app/list.py
vantage_cli/commands/cloud/__init__.py
vantage_cli/commands/cloud/add.py
vantage_cli-0.1.18.dist-info/METADATA
vantage_cli-0.1.18.dist-info/WHEEL
vantage_cli-0.1.18.dist-info/entry_points.txt
vantage_cli-0.1.18.dist-info/licenses/LICENSE
vantage_cli-0.1.18.dist-info/RECORD
