Metadata-Version: 2.4
Name: vantage-cli
Version: 0.1.18
Summary: The Vantage Compute CLI.
Author-email: jamesbeedy <james@vantagecompute.ai>
License: GPL-3.0
License-File: LICENSE
Requires-Python: >=3.11
Requires-Dist: aiohttp>=3.8.0
Requires-Dist: anyio>=3.6.0
Requires-Dist: gql>=4.0.0
Requires-Dist: httpx>=0.28.1
Requires-Dist: juju~=3.6
Requires-Dist: loguru>=0.7.3
Requires-Dist: pendulum>=3.1.0
Requires-Dist: py-buzz>=7.3
Requires-Dist: pydantic>=2.11
Requires-Dist: python-jose[cryptography]>=3.5.0
Requires-Dist: requests-toolbelt>=0.10.0
Requires-Dist: rich>=14.1.0
Requires-Dist: ruamel-yaml
Requires-Dist: snick>=2.1
Requires-Dist: typer>=0.17.4
Provides-Extra: dev
Requires-Dist: black; extra == 'dev'
Requires-Dist: codespell; extra == 'dev'
Requires-Dist: coverage[toml]~=7.8; extra == 'dev'
Requires-Dist: pyright; extra == 'dev'
Requires-Dist: pytest-asyncio>=0.21.0; extra == 'dev'
Requires-Dist: pytest>=7.0.0; extra == 'dev'
Requires-Dist: ruff; extra == 'dev'
